css_class_names.py
css_class_names-0.0.1.dist-info/METADATA
css_class_names-0.0.1.dist-info/RECORD
css_class_names-0.0.1.dist-info/WHEEL
css_class_names-0.0.1.dist-info/top_level.txt
