Metadata-Version: 2.1
Name: css-class-names
Version: 0.0.1
Summary: A python script for css class names conditional generation
Home-page: https://github.com/arturfsousa/css-class-names
Author: Artur Sousa
Author-email: arturfelipe.sousa@gmail.com
License: MIT
Platform: UNKNOWN
Classifier: Programming Language :: Python :: 3
Classifier: License :: OSI Approved :: MIT License
Classifier: Operating System :: OS Independent
